LICENSE
README.md
setup.cfg
setup.py
fastapi_response_log/__init__.py
fastapi_response_log/log_request.py
fastapi_response_log.egg-info/PKG-INFO
fastapi_response_log.egg-info/SOURCES.txt
fastapi_response_log.egg-info/dependency_links.txt
fastapi_response_log.egg-info/requires.txt
fastapi_response_log.egg-info/top_level.txt