Metadata-Version: 2.1
Name: fastapi-response-log
Version: 0.1.3
Summary: A FastAPI route for logging every request
Home-page: https://github.com/aravindalbert/fastapi-log.git
Author: Albert
Author-email: 
License: MIT
Keywords: fastaAPI,logging,response
Platform: UNKNOWN
Classifier: Development Status :: 3 - Alpha
Classifier: Intended Audience :: Developers
Classifier: Topic :: Software Development :: Build Tools
Classifier: License :: OSI Approved :: MIT License
Classifier: Programming Language :: Python :: 3
Classifier: Programming Language :: Python :: 3.6
Classifier: Programming Language :: Python :: 3.7
Classifier: Programming Language :: Python :: 3.8
Classifier: Programming Language :: Python :: 3.9
